crawler_client/__init__.py
crawler_client/api/__init__.py
crawler_client/api/default/__init__.py
crawler_client/api/default/crawl_crawl_post.py
crawler_client/api/default/get_name_name_get.py
crawler_client/api/default/get_task_task_task_id_get.py
crawler_client/client.py
crawler_client/errors.py
crawler_client/models/__init__.py
crawler_client/models/crawl_crawl_post_response_crawl_crawl_post.py
crawler_client/models/crawl_request.py
crawler_client/models/http_validation_error.py
crawler_client/models/validation_error.py
crawler_client/py.typed
crawler_client/types.py
crawler_client-0.1.1.dist-info/METADATA
crawler_client-0.1.1.dist-info/WHEEL
crawler_client-0.1.1.dist-info/RECORD
